.gitignore
LICENSE
Makefile
README.md
architecture.svg
debian_copyright
notes.md
screenshot.png
setup.py
picklecast/__init__.py
picklecast/adapter-latest.js
picklecast/background.jpg
picklecast/display.html
picklecast/index.html
picklecast/localhost.pem
picklecast/picklecast.py
picklecast/picklecast.service
picklecast/version.py
picklecast/webrtc.js
picklecast.egg-info/PKG-INFO
picklecast.egg-info/SOURCES.txt
picklecast.egg-info/dependency_links.txt
picklecast.egg-info/entry_points.txt
picklecast.egg-info/requires.txt
picklecast.egg-info/top_level.txt