Metadata-Version: 2.1
Name: picklecast
Version: 1.0.3.post2
Summary: Share your screen to a projector via web-browser
Home-page: https://github.com/evidlo/picklecast
Author: Evan Widloski
Author-email: evan_github@widloski.com
License: MIT
License-File: LICENSE
Requires-Dist: websockets
